seed2lp/__init__.py
seed2lp/__main__.py
seed2lp/_version.py
seed2lp/argument.py
seed2lp/clingo_lpx.py
seed2lp/color.py
seed2lp/config.yaml
seed2lp/description.py
seed2lp/file.py
seed2lp/flux.py
seed2lp/linear.py
seed2lp/log_conf.yaml
seed2lp/logger.py
seed2lp/metabolite.py
seed2lp/network.py
seed2lp/reaction.py
seed2lp/reasoning.py
seed2lp/reasoningcom.py
seed2lp/reasoninghybrid.py
seed2lp/resmod.py
seed2lp/sbml.py
seed2lp/scope.py
seed2lp/solver.py
seed2lp/temp_flux_com.py
seed2lp/utils.py
seed2lp/asp/atom_for_transfers.lp
seed2lp/asp/community_heuristic.lp
seed2lp/asp/community_search.lp
seed2lp/asp/constraints_targets.lp
seed2lp/asp/definition_atoms.lp
seed2lp/asp/enum-cc.lp
seed2lp/asp/flux.lp
seed2lp/asp/limit_transfers.lp
seed2lp/asp/maximize_flux.lp
seed2lp/asp/maximize_produced_target.lp
seed2lp/asp/minimize.lp
seed2lp/asp/seed-solving.lp
seed2lp/asp/seed_external.lp
seed2lp/asp/show_seeds.lp
seed2lp/asp/show_tranfers.lp
seed2lp/asp/test.lp
seed2lp-2.0.0.dist-info/licenses/LICENCE.txt
tests/__init__.py
tests/fba.py
tests/full_network.py
tests/normalization.py
tests/target.py
tests/utils.py
seed2lp-2.0.0.dist-info/METADATA
seed2lp-2.0.0.dist-info/WHEEL
seed2lp-2.0.0.dist-info/entry_points.txt
seed2lp-2.0.0.dist-info/top_level.txt
seed2lp-2.0.0.dist-info/RECORD
