Metadata-Version: 2.4
Name: seed2lp
Version: 2.0.0
Summary: Seed searching from network as SBML using Logic programming
Home-page: http://github.com/bioasp/seed2lp
Author: Chabname Ghassemi Nedjad
Author-email: chabname.ghassemi-nedjad@inria.fr
License: GPL
Keywords: Answer Set Programming,wrapper,clingo
Classifier: Development Status :: 4 - Beta
Classifier: Intended Audience :: Science/Research
Classifier: Programming Language :: Python :: 3.11
Classifier: Programming Language :: ASP
License-File: LICENCE.txt
Requires-Dist: clyngor>=0.3.18
Requires-Dist: pytest>=4.4.0
Requires-Dist: biseau>=0.0.16
Requires-Dist: cobra
Requires-Dist: clyngor-with-clingo
Requires-Dist: clingo-lpx
Requires-Dist: pyyaml
Requires-Dist: menetools
Requires-Dist: padmet
Requires-Dist: tqdm
Provides-Extra: tests
Requires-Dist: pytest; extra == "tests"
Dynamic: author
Dynamic: author-email
Dynamic: classifier
Dynamic: home-page
Dynamic: license
Dynamic: license-file
Dynamic: summary
